[
    {
        "model": "contest.contestant",
        "pk": 1,
        "fields": {
            "first_name": "fhdfgb",
            "last_name": "fgdfgdfg",
            "gender": "M",
            "year_of_birth": 1999,
            "school": "P",
            "styles": ["D25", "K50"],
            "moderator": 1,
            "contest": 1
        }
  },
  {
      "model": "contest.contestant",
      "pk": 2,
      "fields": {
          "first_name": "jhyuuuh",
          "last_name": "hhhhh",
          "gender": "F",
          "year_of_birth": 2000,
          "school": "P",
          "styles": ["D25", "K50"],
          "moderator": 1,
          "contest": 1
      }
  },
  {
      "model": "contest.contestant",
      "pk": 3,
      "fields": {
          "first_name": "Jakub",
          "last_name": "Maślanka",
          "gender": "M",
          "year_of_birth": 1998,
          "school": "P",
          "styles": ["D25", "K50"],
          "moderator": 1,
          "contest": 1
      }
  },
  {
      "model": "contest.contestant",
      "pk": 4,
      "fields": {
          "first_name": "jhyuuuh",
          "last_name": "hhhhh",
          "gender": "F",
          "year_of_birth": 2002,
          "school": "P",
          "styles": ["D25", "K50"],
          "moderator": 1,
          "contest": 1
      }
  }
]